notas_musicais/__init__.py
notas_musicais/acordes.py
notas_musicais/campo_harmonico.py
notas_musicais/cli.py
notas_musicais/escalas.py
notas_musicais-0.2.1.dist-info/LICENSE
notas_musicais-0.2.1.dist-info/METADATA
notas_musicais-0.2.1.dist-info/WHEEL
notas_musicais-0.2.1.dist-info/entry_points.txt
notas_musicais-0.2.1.dist-info/RECORD
