Metadata-Version: 2.1
Name: notas-musicais
Version: 0.2.1
Summary: Notas musicais é um CLI para ajudar na formação de escalas, acordes e campos harmônicos
License: Beerware
Author: dunossauro
Author-email: mendesxeduardo@gmail.com
Requires-Python: >=3.10,<4.0
Classifier: Development Status :: 5 - Production/Stable
Classifier: Environment :: Console
Classifier: License :: Other/Proprietary License
Classifier: Natural Language :: Portuguese (Brazilian)
Classifier: Programming Language :: Python :: 3
Classifier: Programming Language :: Python :: 3.10
Classifier: Programming Language :: Python :: 3.11
Classifier: Topic :: Education
Requires-Dist: rich (>=13.2.0,<14.0.0)
Requires-Dist: typer (>=0.7.0,<0.8.0)
Project-URL: Bug Tracker, https://github.com/dunossauro/notas-musicais/issues
Project-URL: Código, https://github.com/dunossauro/notas-musicais
Project-URL: Documentação, https://notas-musicais.readthedocs.io/en/latest/
Project-URL: Doação, https://apoia.se/livedepython
